resources/__init__.py
module_resource-0.1.1.dist-info/METADATA
module_resource-0.1.1.dist-info/WHEEL
module_resource-0.1.1.dist-info/RECORD
